subtitlesynchronizer.trained.model.bin
trained.model.spleeter.bin
SubtitleSynchronizer/__init__.py
SubtitleSynchronizer/features.py
SubtitleSynchronizer/find_transform.py
SubtitleSynchronizer/main.py
SubtitleSynchronizer/model.py
SubtitleSynchronizer/preprocessing.py
SubtitleSynchronizer/quality_of_fit.py
SubtitleSynchronizer/srt_io.py
SubtitleSynchronizer/trained_logistic_regression.py
SubtitleSynchronizer-0.0.4.dist-info/LICENSE.txt
SubtitleSynchronizer-0.0.4.dist-info/LICENSE_Old
SubtitleSynchronizer-0.0.4.dist-info/METADATA
SubtitleSynchronizer-0.0.4.dist-info/WHEEL
SubtitleSynchronizer-0.0.4.dist-info/entry_points.txt
SubtitleSynchronizer-0.0.4.dist-info/top_level.txt
SubtitleSynchronizer-0.0.4.dist-info/RECORD
