Metadata-Version: 2.1
Name: SubtitleSynchronizer
Version: 0.0.4
Summary: Automatically synchronize subtitles with video files
Home-page: https://github.com/Subtitle-Synchronizer/SubtitleSynchronizer
Author: Abhishek Khandelwal
License: MIT
Keywords: subtitles syncrhonization srt ffmpeg spleeter
Platform: UNKNOWN
Classifier: Development Status :: 3 - Alpha
Classifier: Environment :: Console
Classifier: Operating System :: POSIX
Classifier: Intended Audience :: End Users/Desktop
Classifier: Topic :: Multimedia
Classifier: License :: OSI Approved :: MIT License
Classifier: Programming Language :: Python :: 2
Classifier: Programming Language :: Python :: 3
Requires-Dist: numpy
Requires-Dist: pysoundfile
Provides-Extra: dev
Requires-Dist: pandas ; extra == 'dev'
Requires-Dist: sklearn ; extra == 'dev'
Provides-Extra: test
Requires-Dist: nose ; extra == 'test'
